[
  {
    "owner_type": "product",
    "namespace": "custom",
    "key": "short_title",
    "name": "Short Title",
    "description": "An optional short version of the product title for display on list pages.",
    "type": "single_line_text_field",
    "validations": {
      "max": 100
    }
  },
  {
    "owner_type": "product",
    "namespace": "custom",
    "key": "sub_title",
    "name": "Sub Title",
    "description": "Use for author, creator, director, etc.",
    "type": "single_line_text_field",
    "validations": {
      "max": 150
    }
  }
]
